kalipto/__init__.py
kalipto/cmdline.py
kalipto/config.py
kalipto-0.1.1.dist-info/METADATA
kalipto-0.1.1.dist-info/RECORD
kalipto-0.1.1.dist-info/WHEEL
kalipto-0.1.1.dist-info/entry_points.txt
kalipto-0.1.1.dist-info/top_level.txt
