Metadata-Version: 2.1
Name: kalipto
Version: 0.1.1
Summary: A steganographic chat over social media
Home-page: https://github.com/reale/kalipto
Author: Roberto Reale
Author-email: rober.reale@gmail.com
License: MIT
Platform: UNKNOWN
Requires-Dist: stegano
Requires-Dist: twitter
Requires-Dist: wget
